LICENSE
README.md
moodle/__init__.py
moodle/__main__.py
moodle/attr.py
moodle/auth/__init__.py
moodle/auth/auth.py
moodle/auth/email/__init__.py
moodle/auth/email/base.py
moodle/auth/email/signup_setting.py
moodle/auth/email/signup_user_response.py
moodle/auth/email/user_custom_field.py
moodle/base/__init__.py
moodle/base/base_moodle.py
moodle/base/general/__init__.py
moodle/base/general/key_message.py
moodle/base/general/key_value.py
moodle/base/general/name_value.py
moodle/base/general/result_error.py
moodle/base/general/status.py
moodle/base/general/success.py
moodle/base/general/type_value.py
moodle/base/general/validated.py
moodle/base/moodle_object.py
moodle/base/name_value.py
moodle/base/preference/__init__.py
moodle/base/preference/notification_component.py
moodle/base/preference/notification_info.py
moodle/base/preference/notification_processor.py
moodle/base/preference/preference_component.py
moodle/base/preference/preference_processor.py
moodle/base/preference/preference_user.py
moodle/base/responses.py
moodle/base/warning.py
moodle/block/__init__.py
moodle/block/block.py
moodle/block/recently_accessed_item.py
moodle/block/starred_course.py
moodle/core/__init__.py
moodle/core/auth/__init__.py
moodle/core/auth/base.py
moodle/core/auth/request_password_reset_response.py
moodle/core/backup/__init__.py
moodle/core/backup/backup_completion_status.py
moodle/core/backup/base.py
moodle/core/backup/copy_data.py
moodle/core/backup/table_row_data.py
moodle/core/badges/__init__.py
moodle/core/badges/badge.py
moodle/core/badges/base.py
moodle/core/block/__init__.py
moodle/core/block/base.py
moodle/core/block/block.py
moodle/core/blog/__init__.py
moodle/core/blog/base.py
moodle/core/blog/blog_entry.py
moodle/core/blog/view_entry.py
moodle/core/calendar/__init__.py
moodle/core/calendar/access_information.py
moodle/core/calendar/allowed_event_types.py
moodle/core/calendar/base.py
moodle/core/calendar/calendar_export_token.py
moodle/core/calendar/course_event.py
moodlepy-0.24.1.dist-info/LICENSE
moodlepy-0.24.1.dist-info/METADATA
moodlepy-0.24.1.dist-info/WHEEL
moodlepy-0.24.1.dist-info/entry_points.txt
moodlepy-0.24.1.dist-info/RECORD
