Metadata-Version: 2.1
Name: moodlepy
Version: 0.24.1
Summary: Python wrapper for moodle web service.
Home-page: https://hexatester.github.io/moodlepy/
License: MIT
Author: hexatester
Author-email: habibrohman@protonmail.com
Requires-Python: >=3.8.10,<4.0.0
Classifier: Development Status :: 4 - Beta
Classifier: Intended Audience :: Developers
Classifier: License :: OSI Approved :: MIT License
Classifier: Operating System :: OS Independent
Classifier: Programming Language :: Python
Classifier: Programming Language :: Python :: 3
Classifier: Programming Language :: Python :: 3.9
Classifier: Programming Language :: Python :: 3.10
Classifier: Programming Language :: Python :: 3.11
Classifier: Programming Language :: Python :: 3.12
Classifier: Programming Language :: Python :: 3.8
Classifier: Topic :: Education
Classifier: Topic :: Software Development :: Libraries :: Python Modules
Provides-Extra: ujson
Requires-Dist: attrs (>=22.2.0,<23.0.0)
Requires-Dist: cattrs (>=22.2.0,<23.0.0)
Requires-Dist: requests (>=2.28.2,<3.0.0)
Requires-Dist: ujson (>=5.4.0,<6.0.0) ; extra == "ujson"
Project-URL: Repository, https://github.com/hexatester/moodlepy
